testinfra/__init__.py
testinfra/host.py
testinfra/main.py
testinfra/plugin.py
testinfra/backend/__init__.py
testinfra/backend/ansible.py
testinfra/backend/base.py
testinfra/backend/chroot.py
testinfra/backend/docker.py
testinfra/backend/kubectl.py
testinfra/backend/local.py
testinfra/backend/lxc.py
testinfra/backend/openshift.py
testinfra/backend/paramiko.py
testinfra/backend/podman.py
testinfra/backend/salt.py
testinfra/backend/ssh.py
testinfra/backend/winrm.py
testinfra/modules/__init__.py
testinfra/modules/addr.py
testinfra/modules/ansible.py
testinfra/modules/base.py
testinfra/modules/blockdevice.py
testinfra/modules/command.py
testinfra/modules/docker.py
testinfra/modules/environment.py
testinfra/modules/file.py
testinfra/modules/group.py
testinfra/modules/interface.py
testinfra/modules/iptables.py
testinfra/modules/mountpoint.py
testinfra/modules/package.py
testinfra/modules/pip.py
testinfra/modules/podman.py
testinfra/modules/process.py
testinfra/modules/puppet.py
testinfra/modules/salt.py
testinfra/modules/service.py
testinfra/modules/socket.py
testinfra/modules/sudo.py
testinfra/modules/supervisor.py
testinfra/modules/sysctl.py
testinfra/modules/systeminfo.py
testinfra/modules/user.py
testinfra/utils/__init__.py
testinfra/utils/ansible_runner.py
pytest_testinfra-10.2.1.dist-info/METADATA
pytest_testinfra-10.2.1.dist-info/WHEEL
pytest_testinfra-10.2.1.dist-info/entry_points.txt
pytest_testinfra-10.2.1.dist-info/licenses/LICENSE
pytest_testinfra-10.2.1.dist-info/RECORD
