Metadata-Version: 2.4
Name: pytest-testinfra
Version: 10.2.1
Summary: Test infrastructures
Author-email: Philippe Pepiot <phil@philpep.org>
License-File: LICENSE
Classifier: Development Status :: 5 - Production/Stable
Classifier: Environment :: Console
Classifier: Framework :: Pytest
Classifier: Intended Audience :: Developers
Classifier: Intended Audience :: Information Technology
Classifier: Intended Audience :: System Administrators
Classifier: License :: OSI Approved :: Apache Software License
Classifier: Operating System :: POSIX
Classifier: Programming Language :: Python
Classifier: Programming Language :: Python :: 3
Classifier: Programming Language :: Python :: 3 :: Only
Classifier: Programming Language :: Python :: 3.9
Classifier: Programming Language :: Python :: 3.10
Classifier: Programming Language :: Python :: 3.11
Classifier: Topic :: Software Development :: Testing
Classifier: Topic :: System :: Systems Administration
Requires-Python: >=3.9
Requires-Dist: pytest>=6
Provides-Extra: ansible
Requires-Dist: ansible; extra == 'ansible'
Provides-Extra: dev
Requires-Dist: alabaster>=0.7.2; extra == 'dev'
Requires-Dist: ansible; extra == 'dev'
Requires-Dist: distro; extra == 'dev'
Requires-Dist: looseversion; extra == 'dev'
Requires-Dist: msgpack; extra == 'dev'
Requires-Dist: mypy; extra == 'dev'
Requires-Dist: paramiko; extra == 'dev'
Requires-Dist: pytest-cov; extra == 'dev'
Requires-Dist: pytest-xdist; extra == 'dev'
Requires-Dist: pywinrm; extra == 'dev'
Requires-Dist: ruff; extra == 'dev'
Requires-Dist: salt; extra == 'dev'
Requires-Dist: sphinx<7.2,>=7.1; extra == 'dev'
Requires-Dist: tornado; extra == 'dev'
Requires-Dist: types-paramiko; extra == 'dev'
Provides-Extra: doc
Requires-Dist: alabaster>=0.7.2; extra == 'doc'
Requires-Dist: sphinx<7.2,>=7.1; extra == 'doc'
Provides-Extra: lint
Requires-Dist: ruff; extra == 'lint'
Provides-Extra: paramiko
Requires-Dist: paramiko; extra == 'paramiko'
Provides-Extra: salt
Requires-Dist: distro; extra == 'salt'
Requires-Dist: looseversion; extra == 'salt'
Requires-Dist: msgpack; extra == 'salt'
Requires-Dist: salt; extra == 'salt'
Requires-Dist: tornado; extra == 'salt'
Provides-Extra: test
Requires-Dist: ansible; extra == 'test'
Requires-Dist: distro; extra == 'test'
Requires-Dist: looseversion; extra == 'test'
Requires-Dist: msgpack; extra == 'test'
Requires-Dist: paramiko; extra == 'test'
Requires-Dist: pytest-cov; extra == 'test'
Requires-Dist: pytest-xdist; extra == 'test'
Requires-Dist: pywinrm; extra == 'test'
Requires-Dist: salt; extra == 'test'
Requires-Dist: tornado; extra == 'test'
Provides-Extra: typing
Requires-Dist: mypy; extra == 'typing'
Requires-Dist: types-paramiko; extra == 'typing'
Provides-Extra: winrm
Requires-Dist: pywinrm; extra == 'winrm'
